extotype/__init__.py
extotype/static/extotype.js
extotype/templates/search.html
extotype-0.7.dist-info/METADATA
extotype-0.7.dist-info/WHEEL
extotype-0.7.dist-info/top_level.txt
extotype-0.7.dist-info/RECORD
