Metadata-Version: 2.1
Name: extotype
Version: 0.7
Requires-Dist: Babel (==2.12.1)
Requires-Dist: Jinja2 (==3.1.2)
Requires-Dist: MarkupSafe (==2.1.2)
Requires-Dist: PyYAML (==6.0)
Requires-Dist: Pygments (==2.14.0)
Requires-Dist: SQLAlchemy (==1.4.47)
Requires-Dist: Sphinx (==6.1.3)
Requires-Dist: aiohttp (==3.8.4)
Requires-Dist: aiosignal (==1.3.1)
Requires-Dist: alabaster (==0.7.13)
Requires-Dist: async-timeout (==4.0.2)
Requires-Dist: attrs (==22.2.0)
Requires-Dist: certifi (==2022.12.7)
Requires-Dist: charset-normalizer (==3.1.0)
Requires-Dist: dataclasses-json (==0.5.7)
Requires-Dist: docutils (==0.19)
Requires-Dist: frozenlist (==1.3.3)
Requires-Dist: greenlet (==2.0.2)
Requires-Dist: idna (==3.4)
Requires-Dist: imagesize (==1.4.1)
Requires-Dist: langchain (==0.0.135)
Requires-Dist: llama-index (==0.5.10)
Requires-Dist: marshmallow-enum (==1.5.1)
Requires-Dist: marshmallow (==3.19.0)
Requires-Dist: multidict (==6.0.4)
Requires-Dist: mypy-extensions (==1.0.0)
Requires-Dist: numpy (==1.24.2)
Requires-Dist: openai (==0.27.4)
Requires-Dist: openapi-schema-pydantic (==1.2.4)
Requires-Dist: packaging (==23.0)
Requires-Dist: pandas (==2.0.0)
Requires-Dist: pydantic (==1.10.7)
Requires-Dist: python-dateutil (==2.8.2)
Requires-Dist: pytz (==2023.3)
Requires-Dist: regex (==2023.3.23)
Requires-Dist: requests (==2.28.2)
Requires-Dist: six (==1.16.0)
Requires-Dist: snowballstemmer (==2.2.0)
Requires-Dist: sphinxcontrib-applehelp (==1.0.4)
Requires-Dist: sphinxcontrib-devhelp (==1.0.2)
Requires-Dist: sphinxcontrib-htmlhelp (==2.0.1)
Requires-Dist: sphinxcontrib-jsmath (==1.0.1)
Requires-Dist: sphinxcontrib-qthelp (==1.0.3)
Requires-Dist: sphinxcontrib-serializinghtml (==1.1.5)
Requires-Dist: tenacity (==8.2.2)
Requires-Dist: tiktoken (==0.3.3)
Requires-Dist: tqdm (==4.65.0)
Requires-Dist: typing-inspect (==0.8.0)
Requires-Dist: typing-extensions (==4.5.0)
Requires-Dist: tzdata (==2023.3)
Requires-Dist: urllib3 (==1.26.15)
Requires-Dist: yarl (==1.8.2)
